Codes/pe.v
module PE#(parameter DATA_WIDTH = 8)(
    input wire clk,
    input wire reset,
    input wire en,
    input wire[DATA_WIDTH-1:0] A_in,
    input wire[DATA_WIDTH-1:0] B_in,
    output reg[DATA_WIDTH-1:0] A_out,
    output reg[DATA_WIDTH-1:0] B_out,
    output reg[2*DATA_WIDTH-1:0] Acc_out
);
wire [(2*DATA_WIDTH)-1:0] product;
    wire [(2*DATA_WIDTH)-1:0] sum;
    assign product = A_in * B_in;
    assign sum = Acc_out + product;
    always @(posedge clk) begin
        if (reset) begin
            A_out <= 0;
            B_out <= 0;
            Acc_out <= 0;
        end else if (en) begin
            A_out <= A_in;
            B_out <= B_in;
            Acc_out <= sum;
        end
    end
endmodule

Codes/systolic_array.v
module systolic_array_2x2 #(
    parameter DATA_WIDTH = 8
)(
    input  wire                      clk,
    input  wire                      reset,
    input  wire                      start,
    
    input  wire [DATA_WIDTH-1:0]     A00, A01, 
    input  wire [DATA_WIDTH-1:0]     A10, A11,
    input  wire [DATA_WIDTH-1:0]     B00, B01, 
    input  wire [DATA_WIDTH-1:0]     B10, B11,
    
    output wire [(2*DATA_WIDTH)-1:0] C00, C01,
    output wire [(2*DATA_WIDTH)-1:0] C10, C11,
    output reg                       done
);

    reg [2:0] cycle_count;
    reg       pe_en;

    always @(posedge clk) begin
        if (reset) begin
            cycle_count <= 0;
            pe_en       <= 0;
            done        <= 0;
        end else if (start) begin
            pe_en <= 1;
            if (cycle_count < 3'd5) begin
                cycle_count <= cycle_count + 1;
            end else begin
                pe_en <= 0; 
                done  <= 1; 
            end
        end
    end

    reg [DATA_WIDTH-1:0] rA0_idx1, rA1_idx0, rA1_idx1;
    reg [DATA_WIDTH-1:0] rB0_idx1, rB1_idx0, rB1_idx1;

    always @(posedge clk) begin
        if (reset) begin
            rA0_idx1 <= 0; rA1_idx0 <= 0; rA1_idx1 <= 0;
            rB0_idx1 <= 0; rB1_idx0 <= 0; rB1_idx1 <= 0;
        end else if (pe_en) begin
            rA0_idx1 <= A01;
            rA1_idx0 <= A10;
            rA1_idx1 <= A11;

            rB0_idx1 <= B10;
            rB1_idx0 <= B01;
            rB1_idx1 <= B11;
        end
    end

    wire [DATA_WIDTH-1:0] pe00_A = (cycle_count == 0) ? A00      : (cycle_count == 1) ? rA0_idx1 : 0;
    wire [DATA_WIDTH-1:0] pe10_A = (cycle_count == 1) ? rA1_idx0 : (cycle_count == 2) ? rA1_idx1 : 0;

    wire [DATA_WIDTH-1:0] pe00_B = (cycle_count == 0) ? B00      : (cycle_count == 1) ? rB0_idx1 : 0;
    wire [DATA_WIDTH-1:0] pe01_B = (cycle_count == 1) ? rB1_idx0 : (cycle_count == 2) ? rB1_idx1 : 0;

    wire [DATA_WIDTH-1:0] net_A00_to_01, net_B00_to_10;
    wire [DATA_WIDTH-1:0] net_A10_to_11, net_B01_to_11;
    wire [DATA_WIDTH-1:0] junk_B01, junk_A10, junk_A11, junk_B11;

    PE #(.DATA_WIDTH(DATA_WIDTH)) pe00 (
        .clk(clk), .reset(reset), .en(pe_en),
        .A_in(pe00_A), .B_in(pe00_B),
        .A_out(net_A00_to_01), .B_out(net_B00_to_10), .Acc_out(C00)
    );

    PE #(.DATA_WIDTH(DATA_WIDTH)) pe01 (
        .clk(clk), .reset(reset), .en(pe_en),
        .A_in(net_A00_to_01), .B_in(pe01_B),
        .A_out(junk_A10), .B_out(net_B01_to_11), .Acc_out(C01)
    );

    PE #(.DATA_WIDTH(DATA_WIDTH)) pe10 (
        .clk(clk), .reset(reset), .en(pe_en),
        .A_in(pe10_A), .B_in(net_B00_to_10),
        .A_out(net_A10_to_11), .B_out(junk_B01), .Acc_out(C10)
    );

    PE #(.DATA_WIDTH(DATA_WIDTH)) pe11 (
        .clk(clk), .reset(reset), .en(pe_en),
        .A_in(net_A10_to_11), .B_in(net_B01_to_11),
        .A_out(junk_A11), .B_out(junk_B11), .Acc_out(C11)
    );

endmodule

Codes/systolic_array_tb.v
`timescale 1ns/1ps

module systolic_array_tb;
    reg clk;
    reg reset;
    reg start;

    reg [7:0] A00, A01, A10, A11;
    reg [7:0] B00, B01, B10, B11;

    wire [15:0] C00, C01, C10, C11;
    wire done;

    systolic_array_2x2 #(.DATA_WIDTH(8)) uut (
        .clk(clk), .reset(reset), .start(start),
        .A00(A00), .A01(A01), .A10(A10), .A11(A11),
        .B00(B00), .B01(B01), .B10(B10), .B11(B11),
        .C00(C00), .C01(C01), .C10(C10), .C11(C11),
        .done(done)
    );

    always #5 clk = ~clk;

    initial begin
        clk = 0;
        reset = 1;
        start = 0;
        
        A00 = 2; A01 = 3;
        A10 = 4; A11 = 5;

        B00 = 1; B01 = 2;
        B10 = 3; B11 = 4;

        #15;
        reset = 0; 
        start = 1; 

        @(posedge done);
        #5;
        
        $display("\n--- Computation Finished! ---");
        $display("Resulting Matrix C:");
        $display("[%3d  %3d]", C00, C01);
        $display("[%3d  %3d]", C10, C11);
        $display("\n");
        
        $finish;
    end
initial begin
    $dumpfile("systolic_wave.vcd"); // Name of the waveform output file
    $dumpvars(0, systolic_array_tb); // Dump all signals in the testbench and below
end
endmodule

simulations/systolic_wave.vcd
$date
	Fri Jul 03 02:49:11 2026
$end
$version
	Icarus Verilog
$end
$timescale
	1ps
$end
$scope module systolic_array_tb $end
$var wire 1 ! done $end
$var wire 16 " C11 [15:0] $end
$var wire 16 # C10 [15:0] $end
$var wire 16 $ C01 [15:0] $end
$var wire 16 % C00 [15:0] $end
$var reg 8 & A00 [7:0] $end
$var reg 8 ' A01 [7:0] $end
$var reg 8 ( A10 [7:0] $end
$var reg 8 ) A11 [7:0] $end
$var reg 8 * B00 [7:0] $end
$var reg 8 + B01 [7:0] $end
$var reg 8 , B10 [7:0] $end
$var reg 8 - B11 [7:0] $end
$var reg 1 . clk $end
$var reg 1 / reset $end
$var reg 1 0 start $end
$scope module uut $end
$var wire 8 1 A00 [7:0] $end
$var wire 8 2 A01 [7:0] $end
$var wire 8 3 A10 [7:0] $end
$var wire 8 4 A11 [7:0] $end
$var wire 8 5 B00 [7:0] $end
$var wire 8 6 B01 [7:0] $end
$var wire 8 7 B10 [7:0] $end
$var wire 8 8 B11 [7:0] $end
$var wire 1 . clk $end
$var wire 1 / reset $end
$var wire 1 0 start $end
$var wire 8 9 pe10_A [7:0] $end
$var wire 8 : pe01_B [7:0] $end
$var wire 8 ; pe00_B [7:0] $end
$var wire 8 < pe00_A [7:0] $end
$var wire 8 = net_B01_to_11 [7:0] $end
$var wire 8 > net_B00_to_10 [7:0] $end
$var wire 8 ? net_A10_to_11 [7:0] $end
$var wire 8 @ net_A00_to_01 [7:0] $end
$var wire 8 A junk_B11 [7:0] $end
$var wire 8 B junk_B01 [7:0] $end
$var wire 8 C junk_A11 [7:0] $end
$var wire 8 D junk_A10 [7:0] $end
$var wire 16 E C11 [15:0] $end
$var wire 16 F C10 [15:0] $end
$var wire 16 G C01 [15:0] $end
$var wire 16 H C00 [15:0] $end
$var parameter 32 I DATA_WIDTH $end
$var reg 3 J cycle_count [2:0] $end
$var reg 1 ! done $end
$var reg 1 K pe_en $end
$var reg 8 L rA0_idx1 [7:0] $end
$var reg 8 M rA1_idx0 [7:0] $end
$var reg 8 N rA1_idx1 [7:0] $end
$var reg 8 O rB0_idx1 [7:0] $end
$var reg 8 P rB1_idx0 [7:0] $end
$var reg 8 Q rB1_idx1 [7:0] $end
$scope module pe00 $end
$var wire 8 R A_in [7:0] $end
$var wire 8 S B_in [7:0] $end
$var wire 1 . clk $end
$var wire 1 K en $end
$var wire 1 / reset $end
$var wire 16 T sum [15:0] $end
$var wire 16 U product [15:0] $end
$var parameter 32 V DATA_WIDTH $end
$var reg 8 W A_out [7:0] $end
$var reg 16 X Acc_out [15:0] $end
$var reg 8 Y B_out [7:0] $end
$upscope $end
$scope module pe01 $end
$var wire 8 Z A_in [7:0] $end
$var wire 8 [ B_in [7:0] $end
$var wire 1 . clk $end
$var wire 1 K en $end
$var wire 1 / reset $end
$var wire 16 \ sum [15:0] $end
$var wire 16 ] product [15:0] $end
$var parameter 32 ^ DATA_WIDTH $end
$var reg 8 _ A_out [7:0] $end
$var reg 16 ` Acc_out [15:0] $end
$var reg 8 a B_out [7:0] $end
$upscope $end
$scope module pe10 $end
$var wire 8 b A_in [7:0] $end
$var wire 8 c B_in [7:0] $end
$var wire 1 . clk $end
$var wire 1 K en $end
$var wire 1 / reset $end
$var wire 16 d sum [15:0] $end
$var wire 16 e product [15:0] $end
$var parameter 32 f DATA_WIDTH $end
$var reg 8 g A_out [7:0] $end
$var reg 16 h Acc_out [15:0] $end
$var reg 8 i B_out [7:0] $end
$upscope $end
$scope module pe11 $end
$var wire 8 j A_in [7:0] $end
$var wire 8 k B_in [7:0] $end
$var wire 1 . clk $end
$var wire 1 K en $end
$var wire 1 / reset $end
$var wire 16 l sum [15:0] $end
$var wire 16 m product [15:0] $end
$var parameter 32 n DATA_WIDTH $end
$var reg 8 o A_out [7:0] $end
$var reg 16 p Acc_out [15:0] $end
$var reg 8 q B_out [7:0] $end
$upscope $end
$upscope $end
$upscope $end
$enddefinitions $end
$comment Show the parameter values. $end
$dumpall
b1000 n
b1000 f
b1000 ^
b1000 V
b1000 I
$end
#0
$dumpvars
bx q
bx p
bx o
bx m
bx l
bx k
bx j
bx i
bx h
bx g
bx e
bx d
bx c
bx b
bx a
bx `
bx _
bx ]
bx \
bx [
bx Z
bx Y
bx X
bx W
bx U
bx T
bx S
bx R
bx Q
bx P
bx O
bx N
bx M
bx L
xK
bx J
bx H
bx G
bx F
bx E
bx D
bx C
bx B
bx A
bx @
bx ?
bx >
bx =
bx <
bx ;
bx :
bx 9
b100 8
b11 7
b10 6
b1 5
b101 4
b100 3
b11 2
b10 1
00
1/
0.
b100 -
b11 ,
b10 +
b1 *
b101 )
b100 (
b11 '
b10 &
bx %
bx $
bx #
bx "
x!
$end
#5000
b0 \
b0 ]
b0 :
b0 [
b0 d
b0 e
b0 9
b0 b
b10 T
b10 U
b10 <
b10 R
b1 ;
b1 S
b0 %
b0 H
b0 X
b0 >
b0 Y
b0 c
b0 @
b0 W
b0 Z
b0 $
b0 G
b0 `
b0 l
b0 m
b0 =
b0 a
b0 k
b0 D
b0 _
b0 #
b0 F
b0 h
b0 B
b0 i
b0 ?
b0 g
b0 j
b0 "
b0 E
b0 p
b0 A
b0 q
b0 C
b0 o
0!
0K
b0 J
b0 Q
b0 P
b0 O
b0 N
b0 M
b0 L
1.
#10000
0.
#15000
b0 <
b0 R
b0 T
b0 U
b0 ;
b0 S
b1 J
1K
1.
10
0/
#20000
0.
#25000
b101 9
b101 b
b100 :
b100 [
b10 J
b100 Q
b10 P
b11 O
b101 N
b100 M
b11 L
1.
#30000
0.
#35000
b0 9
b0 b
b0 :
b0 [
b11 J
b10100 l
b10100 m
b101 ?
b101 g
b101 j
b100 =
b100 a
b100 k
1.
#40000
0.
#45000
b0 =
b0 a
b0 k
b0 m
b0 ?
b0 g
b0 j
b10100 l
b10100 "
b10100 E
b10100 p
b100 A
b100 q
b101 C
b101 o
b100 J
1.
#50000
0.
#55000
b101 J
b0 A
b0 q
b0 C
b0 o
1.
#60000
0.
#65000
1!
0K
1.
