Codes/pe.v
module PE#(parameter DATA_WIDTH = 8)(
    input wire clk,
    input wire reset,
    input wire en,
    input wire[DATA_WIDTH-1:0] A_in,
    input wire[DATA_WIDTH-1:0] B_in,
    output reg[DATA_WIDTH-1:0] A_out,
    output reg[DATA_WIDTH-1:0] B_out,
    output reg[2*DATA_WIDTH-1:0] Acc_out
);
wire [(2*DATA_WIDTH)-1:0] product;
    wire [(2*DATA_WIDTH)-1:0] sum;
    assign product = A_in * B_in;
    assign sum = Acc_out + product;
    always @(posedge clk) begin
        if (reset) begin
            A_out <= 0;
            B_out <= 0;
            Acc_out <= 0;
        end else if (en) begin
            A_out <= A_in;
            B_out <= B_in;
            Acc_out <= sum;
        end
    end
endmodule

Codes/pe_tb.v
`timescale 1ns/1ps

module PE_tb;
reg clk;
reg reset;
reg en;

reg [7:0] A_in;
reg [7:0] B_in;

wire [7:0] A_out;
wire [7:0] B_out;

wire [15:0] Acc_out;
PE #(
    .DATA_WIDTH(8)
) dut (
    .clk(clk),
    .reset(reset),
    .en(en),
    .A_in(A_in),
    .B_in(B_in),
    .A_out(A_out),
    .B_out(B_out),
    .Acc_out(Acc_out)
);
always #5 clk = ~clk;
initial begin
    $dumpfile("wave.vcd");
    $dumpvars(0, PE_tb);
end

initial begin

    clk = 0;
    reset = 1;
    en = 0;

    A_in = 0;
    B_in = 0;

    #10;
    reset = 0;
    en = 1;
    A_in = 2;
    B_in = 3;

    #10;
    A_in = 4;
    B_in = 5;

    #10;
    A_in = 1;
    B_in = 7;

    #10;
    $finish;

end
always @(posedge clk)
begin
    $display("Time=%0t  A=%d  B=%d  Acc=%d",
              $time, A_in, B_in, Acc_out);
end
endmodule

simulations/wave.vcd
$date
	Fri Jul 03 02:35:48 2026
$end
$version
	Icarus Verilog
$end
$timescale
	1ps
$end
$scope module PE_tb $end
$var wire 8 ! B_out [7:0] $end
$var wire 16 " Acc_out [15:0] $end
$var wire 8 # A_out [7:0] $end
$var reg 8 $ A_in [7:0] $end
$var reg 8 % B_in [7:0] $end
$var reg 1 & clk $end
$var reg 1 ' en $end
$var reg 1 ( reset $end
$scope module dut $end
$var wire 8 ) A_in [7:0] $end
$var wire 8 * B_in [7:0] $end
$var wire 1 & clk $end
$var wire 1 ' en $end
$var wire 1 ( reset $end
$var wire 16 + sum [15:0] $end
$var wire 16 , product [15:0] $end
$var parameter 32 - DATA_WIDTH $end
$var reg 8 . A_out [7:0] $end
$var reg 16 / Acc_out [15:0] $end
$var reg 8 0 B_out [7:0] $end
$upscope $end
$upscope $end
$enddefinitions $end
$comment Show the parameter values. $end
$dumpall
b1000 -
$end
#0
$dumpvars
bx 0
bx /
bx .
b0 ,
bx +
b0 *
b0 )
1(
0'
0&
b0 %
b0 $
bx #
bx "
bx !
$end
#5000
b0 +
b0 "
b0 /
b0 !
b0 0
b0 #
b0 .
1&
#10000
0&
b110 +
b110 ,
b11 %
b11 *
b10 $
b10 )
1'
0(
#15000
b1100 +
b110 "
b110 /
b11 !
b11 0
b10 #
b10 .
1&
#20000
0&
b101 %
b101 *
b11010 +
b10100 ,
b100 $
b100 )
#25000
b101110 +
b11010 "
b11010 /
b101 !
b101 0
b100 #
b100 .
1&
#30000
0&
b111 %
b111 *
b100001 +
b111 ,
b1 $
b1 )
#35000
b101000 +
b100001 "
b100001 /
b111 !
b111 0
b1 #
b1 .
1&
